snowflakeio/__init__.py
snowflakeio/engine.py
snowflakeio/lib/__init__.py
snowflakeio/lib/positions_to_buy.py
snowflakeio/py.typed
snowflakeio/tokens.py
snowflakeio/web/__init__.py
snowflakeio/web/api.py
snowflakeio-1.1.4.dist-info/LICENSE
snowflakeio-1.1.4.dist-info/WHEEL
snowflakeio-1.1.4.dist-info/METADATA
snowflakeio-1.1.4.dist-info/RECORD
