Metadata-Version: 2.1
Name: snowflakeio
Version: 1.1.4
Summary: Snowflake IO, a Pythonic Algorithmic Trading Library
Home-page: https://github.com/bradleycm/snowflakeio
License: GNU GPL v3.0
Author: bradleycm
Author-email: chris@riftpay.io
Requires-Python: >=3.8,<3.11
Classifier: Development Status :: 3 - Alpha
Classifier: Intended Audience :: Developers
Classifier: License :: OSI Approved :: GNU General Public License v3 or later (GPLv3+)
Classifier: License :: Other/Proprietary License
Classifier: Operating System :: OS Independent
Classifier: Programming Language :: Python :: 3
Classifier: Programming Language :: Python :: 3.8
Classifier: Programming Language :: Python :: 3.9
Classifier: Topic :: Software Development :: Libraries :: Python Modules
Requires-Dist: beautifulsoup4 (>=4.10.0,<5.0.0)
Requires-Dist: lxml (>=4.6.3,<5.0.0)
Requires-Dist: numpy (>=1.21.2,<2.0.0)
Requires-Dist: pandas (>=1.3.2,<2.0.0)
Requires-Dist: requests (>=2.26.0,<3.0.0)
Project-URL: Repository, https://github.com/bradleycm/snowflakeio
